unomi_query_language/__init__.py
unomi_query_language/errors.py
unomi_query_language/query/__init__.py
unomi_query_language/query/dispatcher.py
unomi_query_language/query/parser.py
unomi_query_language/query/__pycache__/__init__.cpython-37.pyc
unomi_query_language/query/__pycache__/dispatcher.cpython-37.pyc
unomi_query_language/query/__pycache__/parser.cpython-37.pyc
unomi_query_language/query/grammar/grammars.py
unomi_query_language/query/grammar/uql.lark
unomi_query_language/query/grammar/uql_common.lark
unomi_query_language/query/grammar/uql_create_rule.lark
unomi_query_language/query/grammar/uql_create_segment.lark
unomi_query_language/query/grammar/uql_delete.lark
unomi_query_language/query/grammar/uql_expr.lark
unomi_query_language/query/grammar/uql_function.lark
unomi_query_language/query/grammar/uql_insert.lark
unomi_query_language/query/grammar/uql_meta.lark
unomi_query_language/query/grammar/uql_select.lark
unomi_query_language/query/grammar/uql_sort.lark
unomi_query_language/query/grammar/uql_terminals.lark
unomi_query_language/query/grammar/__pycache__/grammars.cpython-37.pyc
unomi_query_language/query/mappers/action_mapper.py
unomi_query_language/query/mappers/condition_type_mapper.py
unomi_query_language/query/mappers/operation_mapper.py
unomi_query_language/query/mappers/uri_mapper.py
unomi_query_language/query/mappers/__pycache__/action_mapper.cpython-37.pyc
unomi_query_language/query/mappers/__pycache__/condition_type_mapper.cpython-37.pyc
unomi_query_language/query/mappers/__pycache__/operation_mapper.cpython-37.pyc
unomi_query_language/query/mappers/__pycache__/uri_mapper.cpython-37.pyc
unomi_query_language/query/mappers/controllers/action_controller.py
unomi_query_language/query/mappers/controllers/__pycache__/action_controller.cpython-37.pyc
unomi_query_language/query/statement_templates/__init__.py
unomi_query_language/query/statement_templates/action_stmt_template.py
unomi_query_language/query/statement_templates/actions_stmt_templates.py
unomi_query_language-0.1.20.dist-info/METADATA
unomi_query_language-0.1.20.dist-info/WHEEL
unomi_query_language-0.1.20.dist-info/top_level.txt
unomi_query_language-0.1.20.dist-info/RECORD
